{
  "class": "gm_bullet_762x39mm_BSD_57N231U",
  "projectile": {
    "model": "gm_bullet_762x39mm_bsd_57n231u",
    "caliber_mm": 7.92,
    "mass_g": 12.5,
    "muzzle_velocity_ms": 290.0,
    "bc_g1": 0.275,
    "cdm_id": "g1",
    "source": {
      "type": "reference_data",
      "reference": "ACE3 ace_ballistics CfgAmmo::gm_bullet_762x39mm_BSD_57N231U",
      "methodology": "Extracted from ACE3 ballistics config via Arma 3 RPT dump.",
      "confidence": "high"
    }
  },
  "chamber_pressure_mpa": 0,
  "notes": "Generated from Arma 3 config dump. ACE3 ballistics: caliber=7.92mm, mass=12.5g, drag=g1, BC=0.275."
}